[ 
   { "ParameterKey": "DockerImage", "ParameterValue": "nginx" },
   { "ParameterKey": "Priority", "ParameterValue": "30" },
   { "ParameterKey": "AppVersionString", "ParameterValue": "another" },
   { "ParameterKey": "Environment", "ParameterValue": "dev" },
   { "ParameterKey": "LiveVersion", "ParameterValue": "True" },
   { "ParameterKey": "RepositoryName", "ParameterValue": "none" },
   { "ParameterKey": "ApplicationName","ParameterValue": "NginxStubApp" },
   { "ParameterKey": "VpcId", "ParameterValue": "VPCID" },
   { "ParameterKey": "AppSubnets", "ParameterValue": "SUBNETS" },
   { "ParameterKey": "ALBStack", "ParameterValue": "test-alb" },
   { "ParameterKey": "DockerPort", "ParameterValue": "80" },
   { "ParameterKey": "SshKeyName", "ParameterValue": "danfarrell@dod" }
]
